[{"id":429,"nombre":"El Andaluz","usuario":"elAndaluztarija","publicacion":0,"megusta":53000,"suma":2,"sector":9,"tipo":"Bolivia","grupo":"Tarija","categoria":"no","rastrear":"medio"},{"id":176,"nombre":"ATB Digital","usuario":"ATBDigital","publicacion":0,"megusta":750786,"suma":1,"sector":1,"tipo":"noticia","grupo":"tv","categoria":"na","rastrear":"medio"},{"id":543,"nombre":"Que No Me Pierda","usuario":"quenomepierdabo","publicacion":0,"megusta":808123,"suma":1,"sector":6,"tipo":"noticia","grupo":"noticia","categoria":"noticia","rastrear":"medio"},{"id":565,"nombre":"Mauricio Israel Camacho Salguero","usuario":"mauricasal","publicacion":0,"megusta":3800,"suma":1,"sector":7,"tipo":"derecha","grupo":"derecha","categoria":"derecha","rastrear":"medio"},{"id":633,"nombre":"Informándote","usuario":"informandoteTrinidad","publicacion":0,"megusta":106700,"suma":1,"sector":11,"tipo":"Bolivia","grupo":"Beni","categoria":"Beni","rastrear":"medio"},{"id":85,"nombre":"La Nota","usuario":"LaNotaBolivia","publicacion":0,"megusta":24660,"suma":1,"sector":13,"tipo":"Bolivia","grupo":"Bolivia","categoria":"na","rastrear":"medio"},{"id":637,"nombre":"NOTI RIBER","usuario":"NOTI-RIBER-435932830125753","publicacion":0,"megusta":154800,"suma":1,"sector":10,"tipo":"Bolivia","grupo":"Beni","categoria":"Beni","rastrear":"medio"},{"id":584,"nombre":"Chaco Al Día","usuario":"profile.php?id=100064226527051","publicacion":0,"megusta":3200,"suma":1,"sector":12,"tipo":"Bolivia","grupo":"Tarija","categoria":"Tarija","rastrear":"medio"},{"id":163,"nombre":"Agencia Boliviana de Información","usuario":"ABI.Bolivia","publicacion":0,"megusta":14182,"suma":0,"sector":1,"tipo":"noticia","grupo":"noticia","categoria":"na","rastrear":"medio"},{"id":440,"nombre":"Ahoradigital","usuario":"ahoradigi","publicacion":0,"megusta":45150,"suma":0,"sector":5,"tipo":"noticia","grupo":"Tarija","categoria":"no","rastrear":"medio"},{"id":426,"nombre":"Periódico Ahora El Pueblo","usuario":"AhoraElPueblo","publicacion":0,"megusta":7419,"suma":0,"sector":4,"tipo":"noticia","grupo":"noticia","categoria":"no","rastrear":"medio"},{"id":8,"nombre":"ANF Noticias Fides","usuario":"ANFidesBolivia","publicacion":0,"megusta":337134,"suma":0,"sector":5,"tipo":"noticia","grupo":"ns","categoria":"na","rastrear":"medio"},{"id":259,"nombre":"Periódico Digital Bolivia Nueva","usuario":"bolivianuevadigital","publicacion":0,"megusta":17890,"suma":0,"sector":5,"tipo":"noticia","grupo":"Bolivia","categoria":"na","rastrear":"medio"},{"id":154,"nombre":"Radios de los Pueblos Originarios","usuario":"BoliviaRpos","publicacion":0,"megusta":13347,"suma":0,"sector":4,"tipo":"noticia","grupo":"tv","categoria":"na","rastrear":"medio"},{"id":59,"nombre":"Bolivia tv","usuario":"BoliviatvOficial","publicacion":0,"megusta":619224,"suma":0,"sector":4,"tipo":"noticia","grupo":"tv","categoria":"na","rastrear":"medio"},{"id":388,"nombre":"Brujula Digital Bolivia","usuario":"brujuladigitalbolivia","publicacion":0,"megusta":21894,"suma":0,"sector":4,"tipo":"noticia","grupo":"notica","categoria":"na","rastrear":"medio"},{"id":416,"nombre":"Cadena A Red Nacional","usuario":"cadenaarednacional","publicacion":0,"megusta":487944,"suma":0,"sector":6,"tipo":"noticia","grupo":"noticia","categoria":"no","rastrear":"medio"},{"id":9,"nombre":"Correo del Sur","usuario":"correodelsurcom","publicacion":0,"megusta":450940,"suma":0,"sector":4,"tipo":"noticia","grupo":"ns","categoria":"na","rastrear":"medio"},{"id":164,"nombre":"Detrás de la Verdad sin Censura","usuario":"detrasdelaverdadsincensuraoficial","publicacion":0,"megusta":51693,"suma":0,"sector":4,"tipo":"noticia","grupo":"comu","categoria":"na","rastrear":"medio"},{"id":417,"nombre":"DiarioHoybolivia","usuario":"DiarioHoybolivia","publicacion":0,"megusta":37688,"suma":0,"sector":1,"tipo":"noticia","grupo":"noticia","categoria":"no","rastrear":"medio"}]